rexdsb/__init__.py
rexdsb-0.0.14.dist-info/LICENSE
rexdsb-0.0.14.dist-info/METADATA
rexdsb-0.0.14.dist-info/WHEEL
rexdsb-0.0.14.dist-info/top_level.txt
rexdsb-0.0.14.dist-info/RECORD
