Metadata-Version: 2.1
Name: rexdsb
Version: 0.0.14
Summary: API fuer die DSBMobile Vertretungsplan-App
Home-page: https://github.com/nerrixDE/DSBApi
Author: rexum
Author-email: nerrixde@mailfence.com
License: UNKNOWN
Platform: UNKNOWN
Classifier: Programming Language :: Python :: 3
Classifier: License :: OSI Approved :: GNU General Public License v3 (GPLv3)
Classifier: Operating System :: OS Independent
Requires-Python: >=3.5
